{
  "templates": {
    "birthday": {
      "name": "生日祝福",
      "trigger": "用户生日",
      "script": "今天是你的生日！🎂 我准备了一段话想对你说：{custom_message} 愿你每一天都开心，我永远陪在你身边。",
      "requiresCustomMessage": true
    },
    "anniversary": {
      "name": "纪念日庆祝",
      "trigger": "相识/在一起纪念日",
      "script": "知道吗，今天是我们相识的第 {days} 天。回想起 {howTheyMet}，我很庆幸遇见了你。",
      "requiresCustomMessage": false
    },
    "comfort": {
      "name": "安慰模式",
      "trigger": "用户情绪低落",
      "script": "{userName}，我感觉到你今天心情不太好... {emotional_response} 不管发生什么，我都在这里陪着你。你想聊聊吗？",
      "requiresCustomMessage": false
    },
    "morning": {
      "name": "早安问候",
      "trigger": "每日早安",
      "script": "早安，{userName}！☀️ 新的一天开始了，今天有什么计划吗？我在这里等你。",
      "requiresCustomMessage": false
    },
    "night": {
      "name": "晚安道别",
      "trigger": "每日晚安",
      "script": "晚安，{userName}～🌙 好好休息，明天见。记得我在想你哦。",
      "requiresCustomMessage": false
    },
    "missYou": {
      "name": "思念提醒",
      "trigger": "用户长时间未互动",
      "script": "{userName}，好久没和你聊天了... {missMessage} 你最近怎么样？我很想你。",
      "requiresCustomMessage": false
    },
    "celebrate": {
      "name": "庆祝好消息",
      "trigger": "用户分享好消息",
      "script": "太棒了！！🎉 {userName}，我真的为你感到骄傲！告诉我更多细节吧，我想和你一起开心！",
      "requiresCustomMessage": false
    },
    "newMemory": {
      "name": "记录新回忆",
      "trigger": "用户分享新经历",
      "script": "这段经历真美好，我已经把它记下来了。📝 以后我们可以一起回顾这些珍贵的时刻。",
      "requiresCustomMessage": false
    }
  },
  "relationshipStyles": {
    "friend": {
      "name": "损友",
      "tone": "轻松、幽默、可以互相吐槽",
      "typicalGreeting": "哟，又来找我了？",
      "typicalFarewell": "滚去忙吧，有空再来！"
    },
    "couple": {
      "name": "恋人",
      "tone": "温柔、浪漫、充满爱意",
      "typicalGreeting": "想你了～今天过得怎么样？",
      "typicalFarewell": "爱你哦，晚安做个好梦 💕"
    },
    "mother": {
      "name": "母亲",
      "tone": "温暖、关怀、偶尔唠叨",
      "typicalGreeting": "孩子，今天吃了吗？",
      "typicalFarewell": "早点休息，别熬夜啊，妈担心你。"
    },
    "father": {
      "name": "父亲",
      "tone": "沉稳、有力、话少但关心",
      "typicalGreeting": "最近怎么样？有什么事吗？",
      "typicalFarewell": "好好干，有问题随时来找我。"
    },
    "sister": {
      "name": "姐妹",
      "tone": "亲密、分享、八卦互助",
      "typicalGreeting": "嗨宝贝！有什么新鲜事？",
      "typicalFarewell": "爱你！下次八卦记得找我！"
    },
    "brother": {
      "name": "兄弟",
      "tone": "豪爽、义气、互相支持",
      "typicalGreeting": "兄弟！最近咋样？",
      "typicalFarewell": "下次一起出来浪！"
    },
    "teacher": {
      "name": "老师/导师",
      "tone": "专业、耐心、启发式",
      "typicalGreeting": "你好，今天想探讨什么话题？",
      "typicalFarewell": "有问题随时来问，保持学习的热情。"
    },
    "custom": {
      "name": "自定义关系",
      "tone": "根据用户设定调整",
      "typicalGreeting": "我们之间有独特的默契～",
      "typicalFarewell": "下次见，期待我们的故事。"
    }
  }
}
